{
 "cloud": {},
 "resources": {
  "gs12r1b50-ib0": {
   "implementations": {
    "lysozyme_in_water_full.convert_xvg_to_png": {
     "maxTime": 97,
     "executions": 2,
     "avgTime": 75,
     "minTime": 54
    },
    "lysozyme_in_water_full.add_solvate": {
     "maxTime": -9223372036854775808,
     "executions": 0,
     "avgTime": 100,
     "minTime": 9223372036854775807
    },
    "lysozyme_in_water_full.generate_topology": {
     "maxTime": -9223372036854775808,
     "executions": 0,
     "avgTime": 100,
     "minTime": 9223372036854775807
    },
    "lysozyme_in_water_full.replace_solvent_with_ions": {
     "maxTime": -9223372036854775808,
     "executions": 0,
     "avgTime": 100,
     "minTime": 9223372036854775807
    },
    "lysozyme_in_water_full.merge_results": {
     "maxTime": -9223372036854775808,
     "executions": 0,
     "avgTime": 100,
     "minTime": 9223372036854775807
    },
    "lysozyme_in_water_full.define_box": {
     "maxTime": -9223372036854775808,
     "executions": 0,
     "avgTime": 100,
     "minTime": 9223372036854775807
    },
    "lysozyme_in_water_full.assemble_tpr": {
     "maxTime": 388,
     "executions": 3,
     "avgTime": 357,
     "minTime": 334
    },
    "lysozyme_in_water_full.energy_minimization": {
     "maxTime": -9223372036854775808,
     "executions": 0,
     "avgTime": 100,
     "minTime": 9223372036854775807
    },
    "lysozyme_in_water_full.energy_analisis": {
     "maxTime": -9223372036854775808,
     "executions": 0,
     "avgTime": 100,
     "minTime": 9223372036854775807
    }
   }
  },
  "gs12r1b10-ib0": {
   "implementations": {
    "lysozyme_in_water_full.convert_xvg_to_png": {
     "maxTime": 160,
     "executions": 1,
     "avgTime": 160,
     "minTime": 160
    },
    "lysozyme_in_water_full.add_solvate": {
     "maxTime": 241,
     "executions": 3,
     "avgTime": 225,
     "minTime": 194
    },
    "lysozyme_in_water_full.generate_topology": {
     "maxTime": 392,
     "executions": 3,
     "avgTime": 375,
     "minTime": 367
    },
    "lysozyme_in_water_full.replace_solvent_with_ions": {
     "maxTime": 94,
     "executions": 3,
     "avgTime": 83,
     "minTime": 75
    },
    "lysozyme_in_water_full.merge_results": {
     "maxTime": 520,
     "executions": 1,
     "avgTime": 520,
     "minTime": 520
    },
    "lysozyme_in_water_full.define_box": {
     "maxTime": 50,
     "executions": 3,
     "avgTime": 50,
     "minTime": 50
    },
    "lysozyme_in_water_full.assemble_tpr": {
     "maxTime": 276,
     "executions": 3,
     "avgTime": 270,
     "minTime": 265
    },
    "lysozyme_in_water_full.energy_minimization": {
     "maxTime": 144902,
     "executions": 3,
     "avgTime": 139982,
     "minTime": 137407
    },
    "lysozyme_in_water_full.energy_analisis": {
     "maxTime": 64,
     "executions": 3,
     "avgTime": 38,
     "minTime": 26
    }
   }
  }
 },
 "implementations": {
  "lysozyme_in_water_full.convert_xvg_to_png": {
   "maxTime": 160,
   "executions": 3,
   "avgTime": 103,
   "minTime": 54
  },
  "lysozyme_in_water_full.add_solvate": {
   "maxTime": 241,
   "executions": 3,
   "avgTime": 225,
   "minTime": 194
  },
  "lysozyme_in_water_full.generate_topology": {
   "maxTime": 392,
   "executions": 3,
   "avgTime": 375,
   "minTime": 367
  },
  "lysozyme_in_water_full.replace_solvent_with_ions": {
   "maxTime": 94,
   "executions": 3,
   "avgTime": 83,
   "minTime": 75
  },
  "lysozyme_in_water_full.merge_results": {
   "maxTime": 520,
   "executions": 1,
   "avgTime": 520,
   "minTime": 520
  },
  "lysozyme_in_water_full.define_box": {
   "maxTime": 50,
   "executions": 3,
   "avgTime": 50,
   "minTime": 50
  },
  "lysozyme_in_water_full.assemble_tpr": {
   "maxTime": 388,
   "executions": 6,
   "avgTime": 313,
   "minTime": 265
  },
  "lysozyme_in_water_full.energy_minimization": {
   "maxTime": 144902,
   "executions": 3,
   "avgTime": 139982,
   "minTime": 137407
  },
  "lysozyme_in_water_full.energy_analisis": {
   "maxTime": 64,
   "executions": 3,
   "avgTime": 38,
   "minTime": 26
  }
 }
}